cx_releaser/__init__.py
cx_releaser/config/__init__.py
cx_releaser/config/config.py
cx_releaser/scripts/__init__.py
cx_releaser/scripts/command.py
cx_releaser/scripts/push.py
cx_releaser/scripts/rollback.py
cx_releaser/src/__init__.py
cx_releaser/src/docker_registry.py
cx_releaser/src/release.py
tests/__init__.py
tests/unit/__init__.py
tests/unit/conftest.py
tests/unit/test_release_push.py
tests/unit/test_release_rollback.py
cx_releaser-0.16.0.dist-info/METADATA
cx_releaser-0.16.0.dist-info/WHEEL
cx_releaser-0.16.0.dist-info/entry_points.txt
cx_releaser-0.16.0.dist-info/top_level.txt
cx_releaser-0.16.0.dist-info/RECORD
