Metadata-Version: 2.1
Name: cx-releaser
Version: 0.16.0
Summary: Python SDK to interact with docker registries
Home-page: https://github.com/CiscoAandI/cx_releaser/
Author: Aleksander Winski
Author-email: awinski@cisco.com
Project-URL: Bug Reports, https://github.com/CiscoAandI/cx_releaser/issues
Project-URL: Source, https://github.com/CiscoAandI/cx_releaser/
Keywords: cx releaser
Classifier: Topic :: Software Development :: Build Tools
Requires-Python: >=3.6
Requires-Dist: boto3 (==1.20.47)
Requires-Dist: docker (==5.0.3)
Requires-Dist: PyYaml (>=5.4.0)
Requires-Dist: semantic-version (==2.9.0)
Requires-Dist: docker-compose (==1.29.2)
